laserstudio/__init__.py
laserstudio/__main__.py
laserstudio/icons/fontawesome-free/arrow-pointer-solid.svg
laserstudio/icons/fontawesome-free/arrows-to-dot-solid.svg
laserstudio/icons/fontawesome-free/directions-solid.svg
laserstudio/icons/fontawesome-free/forward-step-solid.svg
laserstudio/icons/fontawesome-free/image-regular.svg
laserstudio/icons/fontawesome-free/location-pin-solid.svg
laserstudio/icons/fontawesome-free/magnifying-glass-minus-solid.svg
laserstudio/icons/fontawesome-free/magnifying-glass-plus-solid.svg
laserstudio/icons/fontawesome-free/sliders-solid.svg
laserstudio/icons/fontawesome-free/video-slash-solid.svg
laserstudio/icons/fontawesome-free/video-solid.svg
laserstudio/icons/laser-off.svg
laserstudio/icons/laser-on.svg
laserstudio/icons/location-pin-clear.svg
laserstudio/icons/location-pin-plus.svg
laserstudio/icons/logo.svg
laserstudio/icons/magnifying-glass-all-solid.svg
laserstudio/icons/magnifying-glass-one-solid.svg
laserstudio/icons/obj-10x.png
laserstudio/icons/obj-20x.png
laserstudio/icons/obj-50x.png
laserstudio/icons/obj-5x.png
laserstudio/icons/pin.svg
laserstudio/icons/region.svg
laserstudio/instruments/camera.py
laserstudio/instruments/camera_nit.py
laserstudio/instruments/camera_rest.py
laserstudio/instruments/camera_usb.py
laserstudio/instruments/instrument.py
laserstudio/instruments/instruments.py
laserstudio/instruments/joysticks.py
laserstudio/instruments/joysticksHID.py
laserstudio/instruments/laser.py
laserstudio/instruments/laserdriver.py
laserstudio/instruments/list_serials.py
laserstudio/instruments/pdm.py
laserstudio/instruments/probe.py
laserstudio/instruments/rest_instrument.py
laserstudio/instruments/stage.py
laserstudio/instruments/stage_dummy.py
laserstudio/instruments/stage_rest.py
laserstudio/laserstudio.py
laserstudio/lsapi/__init__.py
laserstudio/lsapi/lsapi.py
laserstudio/lsapi/setup.py
laserstudio/restserver/server.py
laserstudio/utils/colors.py
laserstudio/utils/scanning.py
laserstudio/utils/util.py
laserstudio-1.0.0.post5.dist-info/LICENSE
laserstudio-1.0.0.post5.dist-info/LICENSE.LESSER
laserstudio-1.0.0.post5.dist-info/METADATA
laserstudio-1.0.0.post5.dist-info/WHEEL
laserstudio-1.0.0.post5.dist-info/entry_points.txt
laserstudio-1.0.0.post5.dist-info/RECORD
