Metadata-Version: 2.1
Name: laserstudio
Version: 1.0.0.post5
Summary: Python3 software for hardware evaluation
License: LGPL-3.0-or-later
Author: Olivier Hériveaux
Author-email: olivier.heriveaux@ledger.fr
Requires-Python: >=3.9,<3.13
Classifier: Development Status :: 5 - Production/Stable
Classifier: Intended Audience :: Science/Research
Classifier: License :: OSI Approved :: GNU Lesser General Public License v3 or later (LGPLv3+)
Classifier: Programming Language :: Python :: 3
Classifier: Programming Language :: Python :: 3.9
Classifier: Programming Language :: Python :: 3.10
Classifier: Programming Language :: Python :: 3.11
Classifier: Programming Language :: Python :: 3.12
Classifier: Topic :: Scientific/Engineering
Classifier: Topic :: Security
Classifier: Topic :: System :: Hardware
Requires-Dist: flask (==3.0.3)
Requires-Dist: flask-restx (==1.3.0)
Requires-Dist: hidapi (>=0.14.0,<0.15.0)
Requires-Dist: numpy (==1.26.4)
Requires-Dist: opencv-python (==4.9.0.80)
Requires-Dist: pillow (==10.4.0)
Requires-Dist: pypdm (==1.1)
Requires-Dist: pyqt6 (>=6.0)
Requires-Dist: pystages (==1.2)
Requires-Dist: pyusb (==1.2.1)
Requires-Dist: pyyaml (==6.0.1)
Requires-Dist: requests (>=2.32.3,<3.0.0)
Requires-Dist: shapely (>=2.0.5,<3.0.0)
Requires-Dist: triangle (==20230923)
Project-URL: Documentation, https://laserstudio.readthedocs.org/
